[{"id":"5517991134416@s.whatsapp.net","xp":-4384,"msg":390,"level":1},{"id":"555491217705@s.whatsapp.net","xp":506,"msg":1,"level":1},{"id":"556282326836@s.whatsapp.net","xp":1519,"msg":1,"level":1},{"id":"5521986105469@s.whatsapp.net","xp":2525,"msg":1,"level":1},{"id":"556699184376@s.whatsapp.net","xp":502,"msg":1,"level":1},{"id":"553186220057@s.whatsapp.net","xp":103510,"msg":-109,"level":4},{"id":"5514998430165@s.whatsapp.net","xp":5531,"msg":1,"level":1},{"id":"558184410488@s.whatsapp.net","xp":3025,"msg":1,"level":1},{"id":"5521999053515@s.whatsapp.net","xp":2515,"msg":1,"level":1},{"id":"553198004347@s.whatsapp.net","xp":33910,"msg":-89,"level":3},{"id":"553799697886@s.whatsapp.net","xp":11102,"msg":-29,"level":2},{"id":"5527996591035@s.whatsapp.net","xp":92271,"msg":-259,"level":7},{"id":"556699555387@s.whatsapp.net","xp":24732,"msg":-29,"level":2},{"id":"5511970920014@s.whatsapp.net","xp":2031,"msg":1,"level":1},{"id":"559891222878@s.whatsapp.net","xp":7060,"msg":1,"level":1},{"id":"557588276424@s.whatsapp.net","xp":2022,"msg":1,"level":1},{"id":"555496778267@s.whatsapp.net","xp":3553,"msg":-29,"level":1},{"id":"554796370696@s.whatsapp.net","xp":1007,"msg":1,"level":1},{"id":"557192726310@s.whatsapp.net","xp":23732,"msg":1,"level":2},{"id":"556684306704@s.whatsapp.net","xp":1528,"msg":-29,"level":1},{"id":"553191742359@s.whatsapp.net","xp":2,"msg":-9,"level":1},{"id":"554498117646@s.whatsapp.net","xp":10107,"msg":-9,"level":2},{"id":"5511998356380@s.whatsapp.net","xp":504,"msg":1,"level":1},{"id":"556182428121@s.whatsapp.net","xp":2522,"msg":1,"level":1},{"id":"558299518780@s.whatsapp.net","xp":9592,"msg":1,"level":1},{"id":"553899291420@s.whatsapp.net","xp":3521,"msg":1,"level":1},{"id":"5511986292343@s.whatsapp.net","xp":505,"msg":1,"level":1},{"id":"554195357786@s.whatsapp.net","xp":1019,"msg":1,"level":1},{"id":"5511972219528@s.whatsapp.net","xp":504,"msg":1,"level":1},{"id":"559185096790@s.whatsapp.net","xp":508,"msg":1,"level":1},{"id":"559992043494@s.whatsapp.net","xp":2528,"msg":1,"level":1},{"id":"555197316123@s.whatsapp.net","xp":507,"msg":1,"level":1},{"id":"557599231219@s.whatsapp.net","xp":1016,"msg":1,"level":1},{"id":"554796857273@s.whatsapp.net","xp":510,"msg":1,"level":1},{"id":"559296129976@s.whatsapp.net","xp":510,"msg":1,"level":1},{"id":"5521972541101@s.whatsapp.net","xp":510,"msg":1,"level":1},{"id":"5511980910375@s.whatsapp.net","xp":1003,"msg":1,"level":1},{"id":"559180372444@s.whatsapp.net","xp":3035,"msg":1,"level":1},{"id":"5514997924091@s.whatsapp.net","xp":2010,"msg":-9,"level":1},{"id":"5511930590115@s.whatsapp.net","xp":4532,"msg":1,"level":1},{"id":"557398286857@s.whatsapp.net","xp":2020,"msg":1,"level":1},{"id":"554374009386@s.whatsapp.net","xp":1014,"msg":1,"level":1},{"id":"559984025590@s.whatsapp.net","xp":506,"msg":1,"level":1},{"id":"554784800097@s.whatsapp.net","xp":507,"msg":1,"level":1},{"id":"5511949051934@s.whatsapp.net","xp":506,"msg":1,"level":1},{"id":"557193208992@s.whatsapp.net","xp":9575,"msg":1,"level":1},{"id":"12899023377@s.whatsapp.net","xp":5050,"msg":1,"level":1}]